property_lister/main.py
property_lister/utils/array.py
property_lister/utils/config.py
property_lister/utils/directory.py
property_lister/utils/extractor.py
property_lister/utils/file.py
property_lister/utils/general.py
property_lister/utils/plist.py
property_lister/utils/sql.py
property_lister/utils/validate.py
property_lister-3.3.dist-info/licenses/LICENSE
property_lister-3.3.dist-info/METADATA
property_lister-3.3.dist-info/WHEEL
property_lister-3.3.dist-info/entry_points.txt
property_lister-3.3.dist-info/top_level.txt
property_lister-3.3.dist-info/RECORD
