Metadata-Version: 2.4
Name: property-lister
Version: 3.3
Summary: Extract and convert property list files from SQLite database files and from other property list files.
Author: Ivan Sincek
Project-URL: Homepage, https://github.com/ivan-sincek/property-lister
Classifier: Programming Language :: Python :: 3
Classifier: License :: OSI Approved :: MIT License
Classifier: Operating System :: POSIX :: Linux
Requires-Python: >=3.10
License-File: LICENSE
Requires-Dist: biplist>=1.0.3
Requires-Dist: colorama>=0.4.6
Requires-Dist: termcolor>=2.4.0
Dynamic: license-file
